Panda3DNodeEditor/NodeEditor.py
Panda3DNodeEditor/__init__.py
Panda3DNodeEditor/GUI/MainView.py
Panda3DNodeEditor/GUI/MenuBar.py
Panda3DNodeEditor/GUI/__init__.py
Panda3DNodeEditor/LoadScripts/LoadJSON.py
Panda3DNodeEditor/LoadScripts/__init__.py
Panda3DNodeEditor/NodeCore/NodeConnector.py
Panda3DNodeEditor/NodeCore/NodeManager.py
Panda3DNodeEditor/NodeCore/__init__.py
Panda3DNodeEditor/NodeCore/Nodes/AddNode.py
Panda3DNodeEditor/NodeCore/Nodes/BoolAnd.py
Panda3DNodeEditor/NodeCore/Nodes/BoolNode.py
Panda3DNodeEditor/NodeCore/Nodes/BoolOr.py
Panda3DNodeEditor/NodeCore/Nodes/DivideNode.py
Panda3DNodeEditor/NodeCore/Nodes/MultiplyNode.py
Panda3DNodeEditor/NodeCore/Nodes/NodeBase.py
Panda3DNodeEditor/NodeCore/Nodes/NumericNode.py
Panda3DNodeEditor/NodeCore/Nodes/TestOutNode.py
Panda3DNodeEditor/NodeCore/Nodes/__init__.py
Panda3DNodeEditor/NodeCore/Sockets/BoolSocket.py
Panda3DNodeEditor/NodeCore/Sockets/InSocket.py
Panda3DNodeEditor/NodeCore/Sockets/NumericSocket.py
Panda3DNodeEditor/NodeCore/Sockets/OutSocket.py
Panda3DNodeEditor/NodeCore/Sockets/SocketBase.py
Panda3DNodeEditor/NodeCore/Sockets/__init__.py
Panda3DNodeEditor/SaveScripts/SaveJSON.py
Panda3DNodeEditor/SaveScripts/__init__.py
Panda3DNodeEditor/Tools/JSONTools.py
Panda3DNodeEditor/Tools/__init__.py
Panda3DNodeEditor/icons/Plug.png
Panda3DNodeEditor/icons/PlugConnectedGood.png
Panda3DNodeEditor-22.5.dist-info/LICENSE
Panda3DNodeEditor-22.5.dist-info/METADATA
Panda3DNodeEditor-22.5.dist-info/WHEEL
Panda3DNodeEditor-22.5.dist-info/top_level.txt
Panda3DNodeEditor-22.5.dist-info/RECORD
